mecompyapi/__init__.py
mecompyapi/__version__.py
mecompyapi/example.py
mecompyapi/tec.py
mecompyapi/__pycache__/__init__.cpython-310.pyc
mecompyapi/__pycache__/__version__.cpython-310.pyc
mecompyapi/mecom_core/__init__.py
mecompyapi/mecom_core/com_command_exception.py
mecompyapi/mecom_core/mecom_basic_cmd.py
mecompyapi/mecom_core/mecom_frame.py
mecompyapi/mecom_core/mecom_query_set.py
mecompyapi/mecom_core/mecom_var_convert.py
mecompyapi/mecom_core/statistics.py
mecompyapi/mecom_tec/__init__.py
mecompyapi/mecom_tec/lookup_table/__init__.py
mecompyapi/mecom_tec/lookup_table/lut_cmd.py
mecompyapi/mecom_tec/lookup_table/lut_constants.py
mecompyapi/mecom_tec/lookup_table/lut_exception.py
mecompyapi/mecom_tec/lookup_table/lut_record.py
mecompyapi/mecom_tec/lookup_table/lut_status.py
mecompyapi/mecom_tec/lookup_table/lut_test.py
mecompyapi/mecom_tec/lookup_table/csv/LookupTable Sine ramp_0.1_degC_per_sec.csv
mecompyapi/mecom_tec/lookup_table/csv/__init__.py
mecompyapi/phy_wrapper/__init__.py
mecompyapi/phy_wrapper/int_mecom_phy.py
mecompyapi/phy_wrapper/mecom_phy_ftdi.py
mecompyapi/phy_wrapper/mecom_phy_serial_port.py
mecompyapi-0.0.3.dist-info/AUTHORS
mecompyapi-0.0.3.dist-info/LICENSE
mecompyapi-0.0.3.dist-info/METADATA
mecompyapi-0.0.3.dist-info/WHEEL
mecompyapi-0.0.3.dist-info/top_level.txt
mecompyapi-0.0.3.dist-info/RECORD
