Metadata-Version: 2.1
Name: mecompyapi
Version: 0.0.3
Summary: A Python API for the MeCom protocol by Meerstetter.
Home-page: https://github.com/houlihaj/MeComPyAPI
Author: John Houlihan
Author-email: houlihaj@uci.edu
Project-URL: Bug Tracker, https://github.com/houlihaj/MeComPyAPI/issues
Classifier: Programming Language :: Python :: 3
Classifier: Programming Language :: Python :: 3.9
Classifier: Programming Language :: Python :: 3.10
Classifier: Programming Language :: Python :: 3.11
Classifier: Programming Language :: Python :: 3.12
Classifier: License :: OSI Approved :: MIT License
Classifier: Operating System :: Microsoft :: Windows
Requires-Python: >=3.9
License-File: LICENSE
License-File: AUTHORS
Requires-Dist: pyserial >=3.5
Requires-Dist: pythoncrc >=1.21
Requires-Dist: ftd2xx >=1.3.6
